holeysheet/__init__.py
holeysheet/cli.py
holeysheet/excel.py
holeysheet/extract_data.py
holeysheet/parser.py
holeysheet/schema.py
holeysheet-0.1.3.dist-info/WHEEL
holeysheet-0.1.3.dist-info/METADATA
holeysheet-0.1.3.dist-info/RECORD
