Metadata-Version: 2.1
Name: holeysheet
Version: 0.1.3
Summary: 
Author: Nico Ekkart
Author-email: nekkart@crunchanalytics.be
Requires-Python: >=3.8,<4.0
Classifier: Programming Language :: Python :: 3
Classifier: Programming Language :: Python :: 3.10
Classifier: Programming Language :: Python :: 3.8
Classifier: Programming Language :: Python :: 3.9
Requires-Dist: PyYAML (>=6.0,<7.0)
Requires-Dist: pydantic (>=1.10.2,<2.0.0)
Requires-Dist: pylightxl (>=1.60,<2.0)
Requires-Dist: xlrd (>=2.0.1,<3.0.0)
